deepgram/__init__.py
deepgram/agent/__init__.py
deepgram/agent/client.py
deepgram/agent/raw_client.py
deepgram/agent/v1/__init__.py
deepgram/agent/v1/client.py
deepgram/agent/v1/raw_client.py
deepgram/agent/v1/settings/__init__.py
deepgram/agent/v1/settings/client.py
deepgram/agent/v1/settings/raw_client.py
deepgram/agent/v1/settings/think/__init__.py
deepgram/agent/v1/settings/think/client.py
deepgram/agent/v1/settings/think/models/__init__.py
deepgram/agent/v1/settings/think/models/client.py
deepgram/agent/v1/settings/think/models/raw_client.py
deepgram/agent/v1/settings/think/raw_client.py
deepgram/agent/v1/socket_client.py
deepgram/auth/__init__.py
deepgram/auth/client.py
deepgram/auth/raw_client.py
deepgram/auth/v1/__init__.py
deepgram/auth/v1/client.py
deepgram/auth/v1/raw_client.py
deepgram/auth/v1/tokens/__init__.py
deepgram/auth/v1/tokens/client.py
deepgram/auth/v1/tokens/raw_client.py
deepgram/base_client.py
deepgram/client.py
deepgram/core/__init__.py
deepgram/core/api_error.py
deepgram/core/client_wrapper.py
deepgram/core/datetime_utils.py
deepgram/core/events.py
deepgram/core/file.py
deepgram/core/force_multipart.py
deepgram/core/http_client.py
deepgram/core/http_response.py
deepgram/core/jsonable_encoder.py
deepgram/core/pydantic_utilities.py
deepgram/core/query_encoder.py
deepgram/core/remove_none_from_dict.py
deepgram/core/request_options.py
deepgram/core/serialization.py
deepgram/environment.py
deepgram/errors/__init__.py
deepgram/errors/bad_request_error.py
deepgram/extensions/__init__.py
deepgram/extensions/core/__init__.py
deepgram/extensions/core/instrumented_http.py
deepgram/extensions/core/instrumented_socket.py
deepgram/extensions/core/telemetry_events.py
deepgram/extensions/telemetry/__init__.py
deepgram/extensions/telemetry/batching_handler.py
deepgram/extensions/telemetry/handler.py
deepgram/extensions/telemetry/models.py
deepgram/extensions/telemetry/proto_encoder.py
deepgram/extensions/types/__init__.py
deepgram_sdk-5.1.0.dist-info/LICENSE
deepgram_sdk-5.1.0.dist-info/METADATA
deepgram_sdk-5.1.0.dist-info/WHEEL
deepgram_sdk-5.1.0.dist-info/RECORD
